Metadata-Version: 1.0
Name: gu-bi-dist
Version: 1.0
Summary: Gaussian and Binomial distribution
Home-page: UNKNOWN
Author: Vasanth Kumar
Author-email: vasanth.3656@yahoo.com
License: UNKNOWN
Platform: UNKNOWN
